easy_elasticsearch/ElasticSearchBM25.py
easy_elasticsearch/__init__.py
easy_elasticsearch/examples/__init__.py
easy_elasticsearch/examples/quora.py
easy_elasticsearch-0.0.9.dist-info/LICENSE
easy_elasticsearch-0.0.9.dist-info/METADATA
easy_elasticsearch-0.0.9.dist-info/WHEEL
easy_elasticsearch-0.0.9.dist-info/top_level.txt
easy_elasticsearch-0.0.9.dist-info/RECORD
