Metadata-Version: 2.1
Name: easy-elasticsearch
Version: 0.0.9
Summary: An easy-to-use Elasticsearch BM25 interface
Home-page: https://github.com/kwang2049/easy-elasticsearch
Author: Kexin Wang
Author-email: kexin.wang.2049@gmail.com
License: UNKNOWN
Project-URL: Bug Tracker, https://github.com/kwang2049/easy-elasticsearch/issues
Platform: UNKNOWN
Classifier: Programming Language :: Python :: 3
Classifier: License :: OSI Approved :: Apache Software License
Classifier: Operating System :: OS Independent
Requires-Python: >=3.6
License-File: LICENSE
Requires-Dist: elasticsearch (>=7.9.1)
Requires-Dist: tqdm
Requires-Dist: requests
